wxc_sdk/__init__.py
wxc_sdk/admin_audit/__init__.py
wxc_sdk/all_types.py
wxc_sdk/api_child.py
wxc_sdk/as_api.py
wxc_sdk/as_mpe.py
wxc_sdk/as_rest.py
wxc_sdk/attachment_actions/__init__.py
wxc_sdk/authorizations/__init__.py
wxc_sdk/base.py
wxc_sdk/cdr/__init__.py
wxc_sdk/common/__init__.py
wxc_sdk/common/schedules.py
wxc_sdk/common/selective.py
wxc_sdk/converged_recordings/__init__.py
wxc_sdk/device_configurations/__init__.py
wxc_sdk/devices/__init__.py
wxc_sdk/events/__init__.py
wxc_sdk/groups/__init__.py
wxc_sdk/guests/__init__.py
wxc_sdk/har_writer/__init__.py
wxc_sdk/har_writer/har/__init__.py
wxc_sdk/integration/__init__.py
wxc_sdk/licenses/__init__.py
wxc_sdk/locations/__init__.py
wxc_sdk/me/__init__.py
wxc_sdk/me/barge/__init__.py
wxc_sdk/me/callblock/__init__.py
wxc_sdk/me/callcenter/__init__.py
wxc_sdk/me/callerid/__init__.py
wxc_sdk/me/callpark/__init__.py
wxc_sdk/me/callpickup/__init__.py
wxc_sdk/me/callpolicy/__init__.py
wxc_sdk/me/dnd/__init__.py
wxc_sdk/me/endpoints/__init__.py
wxc_sdk/me/executive/__init__.py
wxc_sdk/me/forwarding/__init__.py
wxc_sdk/me/go_override/__init__.py
wxc_sdk/me/personal_assistant/__init__.py
wxc_sdk/me/recording/__init__.py
wxc_sdk/me/secondary_line/__init__.py
wxc_sdk/me/secondary_line/callcenter/__init__.py
wxc_sdk/me/secondary_line/callerid/__init__.py
wxc_sdk/me/secondary_line/callpark/__init__.py
wxc_sdk/me/secondary_line/callpickup/__init__.py
wxc_sdk/me/secondary_line/endpoints/__init__.py
wxc_sdk/me/secondary_line/forwarding/__init__.py
wxc_sdk/me/secondary_line/recording/__init__.py
wxc_sdk/me/secondary_line/voicemail/__init__.py
wxc_sdk/me/snr/__init__.py
wxc_sdk/me/voicemail/__init__.py
wxc_sdk/meetings/__init__.py
wxc_sdk/meetings/chats/__init__.py
wxc_sdk/meetings/closed_captions/__init__.py
wxc_sdk/meetings/invitees/__init__.py
wxc_sdk/meetings/participants/__init__.py
wxc_sdk/meetings/preferences/__init__.py
wxc_sdk/meetings/qanda/__init__.py
wxc_sdk/meetings/qualities/__init__.py
wxc_sdk-1.27.0.dist-info/LICENSE
wxc_sdk-1.27.0.dist-info/METADATA
wxc_sdk-1.27.0.dist-info/WHEEL
wxc_sdk-1.27.0.dist-info/RECORD
