Metadata-Version: 2.3
Name: wxc_sdk
Version: 1.27.0
Summary: SDK for Webex APIs with special focus on Webex Calling specific endpoints
License: MIT
Keywords: Webex,Webex Calling,Webex Teams,Webex Meetings,Webex Devices,Webex Control Hub,Webex Admin,Webex Site Admin,Webex Site,Webex Site Devices,Python,API,SDK
Author: Johannes Krohn
Author-email: jkrohn@cisco.com
Maintainer: Johannes Krohn
Maintainer-email: jkrohn@cisco.com
Requires-Python: >=3.9,<3.14
Classifier: Development Status :: 5 - Production/Stable
Classifier: Intended Audience :: Developers
Classifier: Intended Audience :: System Administrators
Classifier: License :: OSI Approved :: MIT License
Classifier: Natural Language :: English
Classifier: Programming Language :: Python :: 3
Classifier: Programming Language :: Python :: 3.9
Classifier: Programming Language :: Python :: 3.10
Classifier: Programming Language :: Python :: 3.11
Classifier: Programming Language :: Python :: 3.12
Classifier: Programming Language :: Python :: 3.13
Classifier: Topic :: Communications
Classifier: Topic :: Communications :: Chat
Classifier: Topic :: Communications :: Conferencing
Classifier: Topic :: Communications :: Telephony
Requires-Dist: PyYAML (>=6.0,<7.0)
Requires-Dist: aenum (>=3.1.11,<4.0.0)
Requires-Dist: aiohttp (>=3.8.1,<4.0.0)
Requires-Dist: pydantic (>=2.0.0,<3.0.0)
Requires-Dist: python-dateutil (>=2.8.2,<3.0.0)
Requires-Dist: pytz
Requires-Dist: requests (>=2.27.1,<3.0.0)
Requires-Dist: requests-toolbelt (>=1.0.0,<2.0.0)
Project-URL: Documentation, https://wxc-sdk.readthedocs.io
Project-URL: Homepage, https://github.com/jeokrohn/wxc_sdk
